lightstreamer.py
setup.py
py_lightstreamer.egg-info/PKG-INFO
py_lightstreamer.egg-info/SOURCES.txt
py_lightstreamer.egg-info/dependency_links.txt
py_lightstreamer.egg-info/requires.txt
py_lightstreamer.egg-info/top_level.txt