Metadata-Version: 1.0
Name: py-lightstreamer
Version: 0.2
Summary: Lightstreamer HTTP client for Python.
Home-page: http://github.com/dw/py-lightstreamer/
Author: David Wilson
Author-email: dw@botanicus.net
License: Apache 2
Platform: UNKNOWN
